tkhotreload/__init__.py
tkhotreload/tkhotreload.py
tkhr-0.1.2.dist-info/METADATA
tkhr-0.1.2.dist-info/WHEEL
tkhr-0.1.2.dist-info/licenses/LICENSE
tkhr-0.1.2.dist-info/RECORD
