Metadata-Version: 2.4
Name: tkhr
Version: 0.1.2
Summary: A hot reload implementation for Tkinter applications
Project-URL: Homepage, https://github.com/username/tkhr
Project-URL: Repository, https://github.com/username/tkhr.git
Author: Julian
License-Expression: MIT
License-File: LICENSE
Keywords: development-tools,hot-reload,tkinter
Classifier: Development Status :: 3 - Alpha
Classifier: Intended Audience :: Developers
Classifier: License :: OSI Approved :: MIT License
Classifier: Programming Language :: Python :: 3
Classifier: Programming Language :: Python :: 3.8
Classifier: Programming Language :: Python :: 3.9
Classifier: Programming Language :: Python :: 3.10
Classifier: Programming Language :: Python :: 3.11
Classifier: Programming Language :: Python :: 3.12
Requires-Python: >=3.8
